pysoundings/__init__.py
pysoundings/main.py
pysoundings-0.1.3.dist-info/WHEEL
pysoundings-0.1.3.dist-info/METADATA
pysoundings-0.1.3.dist-info/RECORD
