Metadata-Version: 2.1
Name: pysoundings
Version: 0.1.3
Summary: 
Home-page: https://github.com/dkllrjr/pysoundings
License: MIT
Author: dkllrjr
Author-email: dg.kllr.jr@gmail.com
Requires-Python: >=3.9,<4.0
Classifier: License :: OSI Approved :: MIT License
Classifier: Programming Language :: Python :: 3
Classifier: Programming Language :: Python :: 3.9
Requires-Dist: bs4 (>=0.0.1,<0.0.2)
Requires-Dist: lxml (>=4.6.2,<5.0.0)
Requires-Dist: pandas (>=1.2.1,<2.0.0)
Requires-Dist: requests (>=2.25.1,<3.0.0)
Project-URL: Documentation, https://www.alaskanresearcher.org/pysoundings/pysoundings.html
Project-URL: Repository, https://github.com/dkllrjr/pysoundings
